LICENSE
README.rst
setup.py
sqlexec/__init__.py
sqlexec/constant.py
sqlexec/dialect.py
sqlexec/exec.py
sqlexec/loader.py
sqlexec/log_support.py
sqlexec/page_exec.py
sqlexec/sql_exec.py
sqlexec/sql_support.py
sqlexec/table_exec.py
sqlx_exec.egg-info/PKG-INFO
sqlx_exec.egg-info/SOURCES.txt
sqlx_exec.egg-info/dependency_links.txt
sqlx_exec.egg-info/not-zip-safe
sqlx_exec.egg-info/requires.txt
sqlx_exec.egg-info/top_level.txt
test/test.py