Metadata-Version: 2.1
Name: sqlx-exec
Version: 2.3.4
Summary: A thread safe sql executor for Python with connection pool. It helps you automatically manage connections and transactions. Support MySQL, PostgreSQL, SQLite etc.
Home-page: https://gitee.com/summry/sqlx-exec
Author: summy
Author-email: xiazhongbiao@126.com
License: UNKNOWN
Keywords: SQL,MySQL,PostgreSQL,SQLite,Oracle,SQL Server,Database,Python,RDB
Platform: UNKNOWN
Requires-Python: >=3.5
License-File: LICENSE
